LICENSE
autobot/__init__.py
autobot/__main__.py
autobot/app.py
autobot/core/__init__.py
autobot/core/generator.py
autobot/core/parser.py
autobot/logger.py
autobot/settings.py
autobot/types/__init__.py
autobot/types/condition.py
autobot/types/graph.py
autobot/utils/__init__.py
autobot/utils/answer.py
autobot/utils/callback.py
autobot_tg-0.1.2a1.dist-info/entry_points.txt
autobot_tg-0.1.2a1.dist-info/LICENSE
autobot_tg-0.1.2a1.dist-info/WHEEL
autobot_tg-0.1.2a1.dist-info/METADATA
autobot_tg-0.1.2a1.dist-info/RECORD
