Metadata-Version: 2.1
Name: autobot-tg
Version: 0.1.2a1
Summary: Telegram Bot creation made easy
Home-page: https://github.com/andrewsapw/autobot
License: BSD-3-Clause
Author: Andrew S.
Author-email: andrewsapw@gmail.com
Requires-Python: >=3.10,<4.0
Classifier: License :: OSI Approved :: BSD License
Classifier: Programming Language :: Python :: 3
Classifier: Programming Language :: Python :: 3.10
Classifier: Programming Language :: Python :: 3.11
Requires-Dist: aiogram (>=3.0.0b5,<4.0.0)
Requires-Dist: loguru (>=0.6.0,<0.7.0)
Requires-Dist: networkx (>=2.8.8,<3.0.0)
Requires-Dist: pydantic (>=1.10.2,<2.0.0)
Requires-Dist: python-dotenv (>=0.21.0,<0.22.0)
Requires-Dist: pyyaml (>=6.0,<7.0)
Requires-Dist: tomli (>=2.0.1,<3.0.0)
Requires-Dist: uvloop (>=0.17.0,<0.18.0)
Project-URL: Repository, https://github.com/andrewsapw/autobot
